rasterop/__init__.py
rasterop/tiled_op/__init__.py
rasterop/tiled_op/tiled_raster_op.py
rasterop/tiled_op/operation/__init__.py
rasterop/tiled_op/operation/basic.py
rasterop/tiled_op/operation/mapping.py
rasterop/tiled_op/operation/operation.py
rasterop/tiled_op/operation/s1.py
rasterop-0.9.0.dist-info/METADATA
rasterop-0.9.0.dist-info/WHEEL
rasterop-0.9.0.dist-info/licenses/LICENSE.txt
rasterop-0.9.0.dist-info/RECORD
