Metadata-Version: 2.4
Name: rasterop
Version: 0.9.0
Summary: System to manage deforestation alert system
Project-URL: Homepage, https://ciatgit.ciat.cgiar.org/Data_driven_sustainability_public/terra-i/rasterop#
Project-URL: Issues, https://ciatgit.ciat.cgiar.org/Data_driven_sustainability_public/terra-i/rasterop/-/issues
Author-email: Thibaud Vantalon <t.vantalon@cgiar.org>, Louis Reymondin <l.reymondin@cgiar.org>
Maintainer-email: Thibaud Vantalon <t.vantalon@cgiar.org>, Louis Reymondin <l.reymondin@cgiar.org>
License: MIT License
License-File: LICENSE.txt
Keywords: Monitoring,Remote sensing
Classifier: Development Status :: 4 - Beta
Classifier: Intended Audience :: Developers
Classifier: Intended Audience :: Education
Classifier: Intended Audience :: End Users/Desktop
Classifier: Programming Language :: Python :: 3.12
Classifier: Topic :: Software Development :: Build Tools
Requires-Python: >=3.12
Requires-Dist: numpy
Requires-Dist: pyproj
Requires-Dist: scipy
Requires-Dist: shapely
Requires-Dist: tqdm
